Package/__init__.py
Package/main.py
vishal_makwana_Factorial_of_number_project-1.0.0.dist-info/LICENSE.txt
vishal_makwana_Factorial_of_number_project-1.0.0.dist-info/METADATA
vishal_makwana_Factorial_of_number_project-1.0.0.dist-info/WHEEL
vishal_makwana_Factorial_of_number_project-1.0.0.dist-info/entry_points.txt
vishal_makwana_Factorial_of_number_project-1.0.0.dist-info/top_level.txt
vishal_makwana_Factorial_of_number_project-1.0.0.dist-info/RECORD
