Metadata-Version: 2.1
Name: vishal-makwana-Factorial-of-number-project
Version: 1.0.0
Summary: An sample project which implemnts the factorial functions.
Author-email: vishal <vishal.makwana@crestdatasys.com>
Maintainer-email: vishal <vishal.makwana@crestdatasys.com>
Keywords: vishal,Factorial-of-number-project
Requires-Python: >=3.7
License-File: LICENSE.txt
